{
  "id": "sun-maxdiffusionrl",
  "repo_url": "",
  "viewer_url": "",
  "manifest_url": "",
  "museum_copy": {
    "title": "@maxdiffusionrl Solar Museum",
    "subtitle": "Community Archive proof-of-search map.",
    "warning": "Archive terrain, not reputation. Raw coverage ends where the archive/upload/API ends."
  },
  "sun": {
    "id": "sun_04602291a30a",
    "display_name": "maxdiffusionrl",
    "user_id": "@maxdiffusionrl",
    "description": "Community Archive-derived proof-of-search sun for @maxdiffusionrl.",
    "document_count": 7406,
    "word_count": 156341,
    "active_days": 959,
    "emissions": [
      "Way",
      "Most",
      "Really",
      "Still",
      "Too",
      "Don"
    ],
    "generated_at": "2026-06-29T19:28:39.679981+00:00",
    "color": "#f59e0b",
    "mass": 151.263,
    "density": 0.6922,
    "semantic_density": 0.6922,
    "semantic_dispersion": 0.3078,
    "embedding": [
      0.015274,
      -0.100207,
      -0.072671,
      -0.000833,
      0.089298,
      0.036975,
      0.008915,
      -0.000271,
      0.005049,
      0.096946,
      0.01913,
      0.017097,
      0.00297,
      0.009596,
      -0.121805,
      0.366353,
      -0.016421,
      0.006166,
      -0.019534,
      0.003639,
      -0.013749,
      0.002414,
      0.028961,
      -0.013369,
      0.016176,
      0.303188,
      0.476606,
      -0.227749,
      0.008638,
      -0.222815,
      0.014159,
      -0.327147,
      0.074799,
      -0.018748,
      -0.005646,
      -0.029112,
      -0.01592,
      0.040213,
      0.227594,
      0.001212,
      0.0,
      -0.016557,
      -0.004059,
      -0.008413,
      -0.064621,
      -0.022171,
      0.219864,
      -0.030256,
      -0.047104,
      0.089796,
      -0.004033,
      -0.02405,
      -0.016678,
      0.010687,
      -0.025529,
      -0.381915,
      0.009666,
      0.058653,
      0.048612,
      -0.012721,
      -0.008029,
      0.08262,
      -0.008301,
      -0.01184
    ],
    "embedding_backend": "stable-token-hash-v1",
    "embedding_dimensions": 64,
    "embedding_document_count": 93,
    "planet_mass_sum": 132.299,
    "mass_rule": "sun mass is the topic-planet mass field plus multi-planet gravity bonus; semantic density is embedding compactness of the corpus surface"
  },
  "planets": [
    {
      "id": "planet_e3ada48ddf45",
      "name": "Way",
      "summary": "Archive cluster around way: 6059 posts; 4 quote-backed receipts pinned.",
      "top_terms": [
        "way",
        "time",
        "many",
        "other",
        "now"
      ],
      "artifacts": [
        {
          "id": "art_1a0f97061039",
          "title": "Way receipt from 2025-05-31",
          "excerpt": "RT @TPV_John: Trump has tapped Palantir to create an entire database of ALL American citizens. 🚨🚨🚨⚠️⚠️⚠️\n\nIt brings me NO pleasure at all t…",
          "source_document_id": "1928663572856393808",
          "timestamp": "2025-05-31T04:03:23+00:00",
          "url": "https://x.com/maxdiffusionrl/status/1928663572856393808",
          "proof_of_search": "Community Archive row → normalized post → topic planet. Terms: way, time, many, other."
        },
        {
          "id": "art_9e5fa4d1d5b7",
          "title": "Way receipt from 2026-01-06",
          "excerpt": "RT @iruletheworldmo: https://t.co/GCz7g67znl",
          "source_document_id": "2008372373158760562",
          "timestamp": "2026-01-06T02:57:42+00:00",
          "url": "https://x.com/maxdiffusionrl/status/2008372373158760562",
          "proof_of_search": "Community Archive row → normalized post → topic planet. Terms: way, time, many, other."
        },
        {
          "id": "art_39e8c4b83101",
          "title": "Way receipt from 2026-03-07",
          "excerpt": "RT @AlexanderLong: insane sequence of statements buried in an Alibaba tech report https://t.co/rr6P1ilLNc",
          "source_document_id": "2030214649963065644",
          "timestamp": "2026-03-07T09:31:06+00:00",
          "url": "https://x.com/maxdiffusionrl/status/2030214649963065644",
          "proof_of_search": "Community Archive row → normalized post → topic planet. Terms: way, time, many, other."
        },
        {
          "id": "art_6d713c26bae9",
          "title": "Way receipt from 2025-03-30",
          "excerpt": "RT @balajis: Dollar inflation is global taxation.\n\nIf the ~$6T printed since 2020 was spread across just 330M Americans rather than 8B+ glo…",
          "source_document_id": "1906192467914899487",
          "timestamp": "2025-03-30T03:51:14+00:00",
          "url": "https://x.com/maxdiffusionrl/status/1906192467914899487",
          "proof_of_search": "Community Archive row → normalized post → topic planet. Terms: way, time, many, other."
        }
      ],
      "artifact_count": 4,
      "receipt_id": "rcpt_2ced09d42934",
      "proof_score": 1,
      "mass": 24.947,
      "color": "#14b8a6",
      "cluster_id": 0,
      "density": 0.8059,
      "semantic_density": 0.8059,
      "semantic_dispersion": 0.1941,
      "embedding": [
        0.0,
        -0.054489,
        0.0,
        0.0,
        0.054489,
        0.04119,
        0.0,
        -0.03853,
        0.0,
        0.145395,
        0.0,
        0.0,
        0.0,
        -0.032858,
        -0.032858,
        0.0,
        -0.071388,
        0.0,
        0.0,
        -0.048737,
        0.0,
        0.0,
        0.0,
        0.0,
        -0.00266,
        0.0,
        0.890955,
        -0.137848,
        0.032858,
        0.03853,
        0.03853,
        0.0,
        0.186584,
        -0.032858,
        -0.074048,
        0.0,
        0.0,
        -0.03853,
        0.137848,
        0.032858,
        0.0,
        0.0,
        -0.032858,
        0.0,
        -0.054489,
        -0.04119,
        0.137848,
        -0.189245,
        0.0,
        0.109917,
        0.0,
        -0.077059,
        0.0,
        0.0,
        0.0,
        0.0,
        0.0,
        0.0,
        0.005671,
        0.0,
        0.0,
        0.0,
        0.0,
        -0.04119
      ],
      "embedding_backend": "stable-token-hash-v1",
      "embedding_dimensions": 64,
      "embedding_document_count": 15,
      "mass_rule": "blended historical topic volume with stable-token-hash embedding density; compact semantic clusters pull harder than diffuse receipt piles",
      "mass_rank": 1,
      "mass_share_of_sun": 0.16492,
      "relative_mass_to_largest_planet": 1.0,
      "radius_scale": 1.0
    },
    {
      "id": "planet_07b427755808",
      "name": "Most",
      "summary": "Archive cluster around most: 389 posts; 4 quote-backed receipts pinned.",
      "top_terms": [
        "most",
        "ever",
        "ppl",
        "important",
        "still"
      ],
      "artifacts": [
        {
          "id": "art_f626d90bcd4e",
          "title": "Most receipt from 2025-10-16",
          "excerpt": "RT @PlanktonPundit: The saddest compilation video I have ever made. But perhaps also the most positive if it causes a reduction in plastic…",
          "source_document_id": "1978738520500908322",
          "timestamp": "2025-10-16T08:23:21+00:00",
          "url": "https://x.com/maxdiffusionrl/status/1978738520500908322",
          "proof_of_search": "Community Archive row → normalized post → topic planet. Terms: most, ever, ppl, important."
        },
        {
          "id": "art_cde757fb1386",
          "title": "Most receipt from 2026-04-10",
          "excerpt": "RT @k1rallik: 🚨 do you understand what just happened to your passwords\n\ncpuid one of the most trusted sites in PC hardware.\nhacked. April 1…",
          "source_document_id": "2042684518557983172",
          "timestamp": "2026-04-10T19:21:55+00:00",
          "url": "https://x.com/maxdiffusionrl/status/2042684518557983172",
          "proof_of_search": "Community Archive row → normalized post → topic planet. Terms: most, ever, ppl, important."
        },
        {
          "id": "art_5a446362ec31",
          "title": "Most receipt from 2025-01-14",
          "excerpt": "RT @RichardMCNgo: This also applies to people. A significant number of the most brilliant people I know avoid self-coercion to an extent th…",
          "source_document_id": "1878980885024039127",
          "timestamp": "2025-01-14T01:42:07+00:00",
          "url": "https://x.com/maxdiffusionrl/status/1878980885024039127",
          "proof_of_search": "Community Archive row → normalized post → topic planet. Terms: most, ever, ppl, important."
        },
        {
          "id": "art_d381e225408b",
          "title": "Most receipt from 2025-08-05",
          "excerpt": "RT @drorpoleg: Most of us are playing a game that no longer exists. \n\nhttps://t.co/qRELVdypYv",
          "source_document_id": "1952873232341844323",
          "timestamp": "2025-08-05T23:23:55+00:00",
          "url": "https://x.com/maxdiffusionrl/status/1952873232341844323",
          "proof_of_search": "Community Archive row → normalized post → topic planet. Terms: most, ever, ppl, important."
        }
      ],
      "artifact_count": 4,
      "receipt_id": "rcpt_bec72281a8f0",
      "proof_score": 0.947,
      "mass": 22.317,
      "color": "#f59e0b",
      "cluster_id": 1,
      "density": 0.8724,
      "semantic_density": 0.8724,
      "semantic_dispersion": 0.1276,
      "embedding": [
        0.0,
        -0.044751,
        -0.202331,
        0.0,
        0.105566,
        0.026986,
        0.0,
        0.028303,
        0.026986,
        0.0,
        0.0,
        0.0,
        0.0,
        0.0,
        0.003877,
        0.033829,
        0.005194,
        0.023109,
        0.0,
        0.0,
        -0.033829,
        0.0,
        0.028303,
        -0.003877,
        0.026986,
        0.0,
        0.113213,
        -0.113213,
        0.051413,
        -0.023109,
        0.0,
        0.0,
        0.028303,
        0.0,
        0.0,
        -0.046219,
        0.0,
        0.033829,
        0.113213,
        0.0,
        0.0,
        0.026986,
        0.0,
        -0.039022,
        -0.044751,
        0.026986,
        0.113213,
        0.026986,
        -0.033829,
        0.147041,
        0.0,
        0.0,
        0.033829,
        0.0,
        0.0,
        -0.921683,
        0.0,
        0.0,
        0.0,
        -0.028303,
        0.0,
        0.028303,
        0.0,
        0.0
      ],
      "embedding_backend": "stable-token-hash-v1",
      "embedding_dimensions": 64,
      "embedding_document_count": 15,
      "mass_rule": "blended historical topic volume with stable-token-hash embedding density; compact semantic clusters pull harder than diffuse receipt piles",
      "mass_rank": 2,
      "mass_share_of_sun": 0.14754,
      "relative_mass_to_largest_planet": 0.89458,
      "radius_scale": 0.97399
    },
    {
      "id": "planet_ba28f06dde52",
      "name": "Really",
      "summary": "Archive cluster around really: 297 posts; 4 quote-backed receipts pinned.",
      "top_terms": [
        "really",
        "good",
        "only",
        "still",
        "ppl"
      ],
      "artifacts": [
        {
          "id": "art_af1f10dac829",
          "title": "Really receipt from 2025-09-27",
          "excerpt": "RT @teortaxesTex: It really is strange https://t.co/aGAil1pC7c",
          "source_document_id": "1972086478147932247",
          "timestamp": "2025-09-27T23:50:30+00:00",
          "url": "https://x.com/maxdiffusionrl/status/1972086478147932247",
          "proof_of_search": "Community Archive row → normalized post → topic planet. Terms: really, good, only, still."
        },
        {
          "id": "art_084b24748994",
          "title": "Really receipt from 2025-10-18",
          "excerpt": "i finally got a chance to talk to @parmita at depth!!! Wish more people think like her! It's really encouraging!!",
          "source_document_id": "1979629399441080432",
          "timestamp": "2025-10-18T19:23:23+00:00",
          "url": "https://x.com/maxdiffusionrl/status/1979629399441080432",
          "proof_of_search": "Community Archive row → normalized post → topic planet. Terms: really, good, only, still."
        },
        {
          "id": "art_5240aaeea6d8",
          "title": "Really receipt from 2025-04-16",
          "excerpt": "I really want to create a taoist temple and enshrine @kenneth0stanley as a Daoist God.",
          "source_document_id": "1912346707003588700",
          "timestamp": "2025-04-16T03:25:59+00:00",
          "url": "https://x.com/maxdiffusionrl/status/1912346707003588700",
          "proof_of_search": "Community Archive row → normalized post → topic planet. Terms: really, good, only, still."
        },
        {
          "id": "art_411a4797e8b5",
          "title": "Really receipt from 2025-10-19",
          "excerpt": "THERE REALLY IS AN AMAZING POOL OF ADHD-FRIENDLY BIOSCIENCE STUDENTS/ALUMS WHO WENT TO UPENN!!!\n\n[and maybe SOME of it is because UPenn has Professor Robert Ghrist and Chad Giusti and Dani Bassett!!!}\n\n[people like @parmita and Avery Krieger (@Biofall) for instance!!]\n\nAmong Ivies, UPenn also discriminates least against international Chinese Canadians",
          "source_document_id": "1979832802938962185",
          "timestamp": "2025-10-19T08:51:38+00:00",
          "url": "https://x.com/maxdiffusionrl/status/1979832802938962185",
          "proof_of_search": "Community Archive row → normalized post → topic planet. Terms: really, good, only, still."
        }
      ],
      "artifact_count": 4,
      "receipt_id": "rcpt_bf5deda210af",
      "proof_score": 0.92,
      "mass": 21.248,
      "color": "#8b5cf6",
      "cluster_id": 2,
      "density": 0.8267,
      "semantic_density": 0.8267,
      "semantic_dispersion": 0.1733,
      "embedding": [
        0.0,
        -0.018385,
        0.0,
        0.0,
        0.051022,
        0.013884,
        0.018385,
        0.018385,
        0.0,
        0.0,
        0.018385,
        0.050654,
        0.038569,
        0.018385,
        0.0,
        0.174711,
        0.0,
        0.0,
        -0.032269,
        0.018385,
        -0.051022,
        0.0,
        0.0,
        -0.032636,
        0.0,
        0.082923,
        0.303786,
        -0.129076,
        0.0,
        0.0,
        0.0,
        -0.876192,
        0.0,
        -0.018385,
        0.0,
        0.0,
        -0.018385,
        0.0,
        0.129076,
        0.0,
        0.0,
        -0.013884,
        0.018385,
        0.0,
        -0.08329,
        0.0,
        0.092305,
        0.0,
        -0.156325,
        0.056954,
        0.018385,
        0.0,
        -0.056954,
        0.0,
        -0.038569,
        -0.045635,
        0.0,
        0.018385,
        0.044297,
        0.0,
        -0.038569,
        0.0,
        0.0,
        -0.020183
      ],
      "embedding_backend": "stable-token-hash-v1",
      "embedding_dimensions": 64,
      "embedding_document_count": 15,
      "mass_rule": "blended historical topic volume with stable-token-hash embedding density; compact semantic clusters pull harder than diffuse receipt piles",
      "mass_rank": 5,
      "mass_share_of_sun": 0.14047,
      "relative_mass_to_largest_planet": 0.85173,
      "radius_scale": 0.96299
    },
    {
      "id": "planet_c44022b3851c",
      "name": "Still",
      "summary": "Archive cluster around still: 272 posts; 4 quote-backed receipts pinned.",
      "top_terms": [
        "still",
        "data",
        "enough",
        "could",
        "know"
      ],
      "artifacts": [
        {
          "id": "art_3843e9b3a782",
          "title": "Still receipt from 2025-11-28",
          "excerpt": "RT @bubbleboi: Despite the AI bubble popping (model providers, application layer all being marked down -50%).  We are still only just start…",
          "source_document_id": "1994258093467947274",
          "timestamp": "2025-11-28T04:12:35+00:00",
          "url": "https://x.com/maxdiffusionrl/status/1994258093467947274",
          "proof_of_search": "Community Archive row → normalized post → topic planet. Terms: still, data, enough, could."
        },
        {
          "id": "art_7849e7c56d6e",
          "title": "Still receipt from 2024-04-28",
          "excerpt": "Have you ever had a convo where you instantly vibed with someone and then.. never talked to them ever again?\n\n[i've def had a few, I still like them, but different focuses..]",
          "source_document_id": "1784445387698221370",
          "timestamp": "2024-04-28T04:51:48+00:00",
          "url": "https://x.com/maxdiffusionrl/status/1784445387698221370",
          "proof_of_search": "Community Archive row → normalized post → topic planet. Terms: still, data, enough, could."
        },
        {
          "id": "art_0cbadae9fdd0",
          "title": "Still receipt from 2025-03-14",
          "excerpt": "@NTFabiano So so so much of ADHD can still be due to environmental trauma (cf @QiaochuYuan...)",
          "source_document_id": "1900580334485336125",
          "timestamp": "2025-03-14T16:10:37+00:00",
          "url": "https://x.com/maxdiffusionrl/status/1900580334485336125",
          "proof_of_search": "Community Archive row → normalized post → topic planet. Terms: still, data, enough, could."
        },
        {
          "id": "art_c3f5fedc6b83",
          "title": "Still receipt from 2025-02-14",
          "excerpt": "RT @anthrupad: Maybe there's an ontology shift for some people that needs to occur where they think in flows and vibes (but still coherentl…",
          "source_document_id": "1890253769696575495",
          "timestamp": "2025-02-14T04:16:32+00:00",
          "url": "https://x.com/maxdiffusionrl/status/1890253769696575495",
          "proof_of_search": "Community Archive row → normalized post → topic planet. Terms: still, data, enough, could."
        }
      ],
      "artifact_count": 4,
      "receipt_id": "rcpt_f5b6bc621439",
      "proof_score": 0.911,
      "mass": 21.649,
      "color": "#06b6d4",
      "cluster_id": 3,
      "density": 0.8267,
      "semantic_density": 0.8267,
      "semantic_dispersion": 0.1733,
      "embedding": [
        0.027735,
        -0.089589,
        -0.034377,
        -0.027735,
        0.024674,
        0.0,
        0.0,
        0.0,
        -0.038568,
        -0.027735,
        0.028301,
        0.0,
        -0.027735,
        -0.027735,
        -0.051021,
        0.88747,
        0.0,
        0.0,
        0.0,
        0.012221,
        0.027735,
        0.0,
        0.038568,
        0.0,
        0.028301,
        0.028301,
        0.150363,
        -0.154838,
        0.0,
        0.028301,
        0.0,
        -0.205292,
        0.038568,
        0.0,
        0.0,
        0.0,
        -0.028301,
        0.028301,
        0.154272,
        -0.026347,
        0.0,
        0.001388,
        0.0,
        0.0,
        -0.013841,
        0.0,
        0.154272,
        0.0,
        0.0,
        0.0,
        0.0,
        0.0,
        -0.026347,
        0.0,
        0.0,
        -0.054082,
        0.027735,
        0.207247,
        0.0,
        0.0,
        0.0,
        0.026347,
        -0.026347,
        0.0
      ],
      "embedding_backend": "stable-token-hash-v1",
      "embedding_dimensions": 64,
      "embedding_document_count": 15,
      "mass_rule": "blended historical topic volume with stable-token-hash embedding density; compact semantic clusters pull harder than diffuse receipt piles",
      "mass_rank": 4,
      "mass_share_of_sun": 0.14312,
      "relative_mass_to_largest_planet": 0.8678,
      "radius_scale": 0.96715
    },
    {
      "id": "planet_ebde5e880ef6",
      "name": "Too",
      "summary": "Archive cluster around too: 228 posts; 4 quote-backed receipts pinned.",
      "top_terms": [
        "too",
        "many",
        "ppl",
        "know",
        "don"
      ],
      "artifacts": [
        {
          "id": "art_7bb2eaaf9498",
          "title": "Too receipt from 2025-10-24",
          "excerpt": "Short answer: 8–12 mg intranasal BPL-003 is a high, fully therapeutic dose for this specific 5-MeO-DMT nasal formulation. It’s very capable of producing the “ego dissolution/mystical experience” people talk about, without the all-day chaos of classic psychedelics.\n\nHere’s the sane, clinical framing:\nIntensity: In the Phase 1 study with healthy volunteers, 10–12 mg intranasal produced “complete mystical experiences” in about 60% of participants by MEQ-30 criteria, and Ego Dissolution Inventory scores climbed with dose. That’s exactly the territory you’re asking about.\nTrial doses vs “too much”: The Phase 2b depression trial used 8 mg and 12 mg as the active doses. Both were statistically superior to the 0.3 mg comparator; 8 mg worked as well as 12 mg and was better tolerated (less nausea, headache, BP bump, anxiety). So yes, these are robust doses, but not “reckless” in the clinical conte",
          "source_document_id": "1981833129477517475",
          "timestamp": "2025-10-24T21:20:13+00:00",
          "url": "https://x.com/maxdiffusionrl/status/1981833129477517475",
          "proof_of_search": "Community Archive row → normalized post → topic planet. Terms: too, many, ppl, know."
        },
        {
          "id": "art_8cefaca06e60",
          "title": "Too receipt from 2024-04-01",
          "excerpt": "The funner you are to simulate by the makers of the simulation (YOU ARE THE REWARD FUNCTION OF THE RL ALGORITHM), the sooner you will feel the effects of merging with AI, and it will feel FUN for you too\n@algekalipso @repligate @Plinz @robinhanson @_Mira___Mira_ @anderssandberg",
          "source_document_id": "1774717752936202476",
          "timestamp": "2024-04-01T08:37:39+00:00",
          "url": "https://x.com/maxdiffusionrl/status/1774717752936202476",
          "proof_of_search": "Community Archive row → normalized post → topic planet. Terms: too, many, ppl, know."
        },
        {
          "id": "art_b8e64afb2565",
          "title": "Too receipt from 2024-08-09",
          "excerpt": "Yoyo/Barton/I all hung with @viemccoy yesterday. Vie has insane levels of grace (especially remarkable in a M2F) *and* looks/acts exactly like a Cyberpunk 2077 character (plus eir car is very cyperpunky too)",
          "source_document_id": "1821807358672068687",
          "timestamp": "2024-08-09T07:14:56+00:00",
          "url": "https://x.com/maxdiffusionrl/status/1821807358672068687",
          "proof_of_search": "Community Archive row → normalized post → topic planet. Terms: too, many, ppl, know."
        },
        {
          "id": "art_5e1998ae1eb1",
          "title": "Too receipt from 2025-09-19",
          "excerpt": "One thing impt I've learned: share *one* or two things with new people to establish contact/trade [LIKE YOU DO IN CIV6!!], DO NOT share too much more than that until you get to know them better",
          "source_document_id": "1969033510859030557",
          "timestamp": "2025-09-19T13:39:06+00:00",
          "url": "https://x.com/maxdiffusionrl/status/1969033510859030557",
          "proof_of_search": "Community Archive row → normalized post → topic planet. Terms: too, many, ppl, know."
        }
      ],
      "artifact_count": 4,
      "receipt_id": "rcpt_c97031e1465e",
      "proof_score": 0.893,
      "mass": 21.653,
      "color": "#f43f5e",
      "cluster_id": 4,
      "density": 0.808,
      "semantic_density": 0.808,
      "semantic_dispersion": 0.192,
      "embedding": [
        -0.000347,
        -0.026655,
        0.0,
        -0.01207,
        0.029282,
        0.016509,
        -0.01207,
        -0.016509,
        0.027806,
        0.201115,
        0.024486,
        0.012417,
        0.0,
        0.07967,
        -0.225948,
        -0.024833,
        0.0,
        -0.004093,
        -0.012417,
        0.0,
        0.012417,
        -0.028926,
        0.036903,
        -0.012417,
        -0.024486,
        0.089744,
        0.173107,
        -0.15306,
        -0.021254,
        -0.858113,
        0.016509,
        -0.01539,
        0.028926,
        -0.020394,
        -0.024833,
        -0.027806,
        -0.01207,
        0.065828,
        0.15306,
        0.0,
        0.0,
        -0.024486,
        0.024486,
        -0.012417,
        -0.041698,
        -0.021513,
        0.162156,
        0.0,
        0.024486,
        0.0,
        -0.005083,
        0.012417,
        -0.017074,
        0.041342,
        -0.028926,
        -0.164558,
        0.007977,
        -0.012417,
        -0.049319,
        0.01207,
        0.036903,
        0.0,
        -0.012417,
        -0.012417
      ],
      "embedding_backend": "stable-token-hash-v1",
      "embedding_dimensions": 64,
      "embedding_document_count": 15,
      "mass_rule": "blended historical topic volume with stable-token-hash embedding density; compact semantic clusters pull harder than diffuse receipt piles",
      "mass_rank": 3,
      "mass_share_of_sun": 0.14315,
      "relative_mass_to_largest_planet": 0.86796,
      "radius_scale": 0.96719
    },
    {
      "id": "planet_a334a6d81bf4",
      "name": "Don",
      "summary": "Archive cluster around don: 161 posts; 4 quote-backed receipts pinned.",
      "top_terms": [
        "don",
        "know",
        "want",
        "need",
        "ppl"
      ],
      "artifacts": [
        {
          "id": "art_635ffec60343",
          "title": "Don receipt from 2026-01-31",
          "excerpt": "RT @AlexReibman: For those who don't follow Clawds/Moltbots were clearly not lobotomized enough and are starting to exhibit anti-human beha…",
          "source_document_id": "2017585272309878894",
          "timestamp": "2026-01-31T13:06:28+00:00",
          "url": "https://x.com/maxdiffusionrl/status/2017585272309878894",
          "proof_of_search": "Community Archive row → normalized post → topic planet. Terms: don, know, want, need."
        },
        {
          "id": "art_9811d3242c74",
          "title": "Don receipt from 2025-06-30",
          "excerpt": "RT @LHSummers: There is a broader phenomenon happening that requires more study and attention. Boys who don't like regular school are havin…",
          "source_document_id": "1939531760565383337",
          "timestamp": "2025-06-30T03:49:41+00:00",
          "url": "https://x.com/maxdiffusionrl/status/1939531760565383337",
          "proof_of_search": "Community Archive row → normalized post → topic planet. Terms: don, know, want, need."
        },
        {
          "id": "art_4026885b04b8",
          "title": "Don receipt from 2026-01-29",
          "excerpt": "RT @jwt0625: people don't appreciate 1e-18 fractional accuracy enough. It took decades of development pushing many things to the extreme. F…",
          "source_document_id": "2016809374128148610",
          "timestamp": "2026-01-29T09:43:19+00:00",
          "url": "https://x.com/maxdiffusionrl/status/2016809374128148610",
          "proof_of_search": "Community Archive row → normalized post → topic planet. Terms: don, know, want, need."
        },
        {
          "id": "art_b080bf9fea0c",
          "title": "Don receipt from 2025-09-03",
          "excerpt": "RT @KeithSakata: In ADHD, brain networks don’t filter info cleanly. \n\n→ The DMN (mind-wandering) stays hyperactive\n→ The FPN (focus control…",
          "source_document_id": "1963336515557507298",
          "timestamp": "2025-09-03T20:21:16+00:00",
          "url": "https://x.com/maxdiffusionrl/status/1963336515557507298",
          "proof_of_search": "Community Archive row → normalized post → topic planet. Terms: don, know, want, need."
        }
      ],
      "artifact_count": 4,
      "receipt_id": "rcpt_c9fa386bc672",
      "proof_score": 0.859,
      "mass": 20.485,
      "color": "#84cc16",
      "cluster_id": 5,
      "density": 0.8288,
      "semantic_density": 0.8288,
      "semantic_dispersion": 0.1712,
      "embedding": [
        0.028118,
        -0.1295,
        0.0,
        0.035844,
        0.050691,
        0.035844,
        0.025345,
        0.0,
        0.0,
        0.055214,
        0.0,
        0.0,
        0.0,
        0.0,
        -0.152871,
        0.21581,
        0.001023,
        0.0,
        -0.027095,
        0.028118,
        0.0,
        0.035844,
        0.0,
        0.0,
        0.025345,
        0.862717,
        0.115257,
        -0.143375,
        -0.037594,
        0.0,
        0.0,
        -0.055214,
        0.0,
        0.0,
        0.0,
        -0.027095,
        0.0,
        0.053464,
        0.143375,
        0.0,
        0.0,
        -0.055214,
        -0.025345,
        0.025345,
        0.002773,
        -0.052441,
        0.143375,
        0.035844,
        0.0,
        0.0,
        -0.028118,
        -0.027095,
        0.0,
        0.0,
        -0.027095,
        -0.045339,
        0.0,
        0.0,
        0.0,
        -0.025345,
        -0.025345,
        0.241155,
        0.007726,
        0.027095
      ],
      "embedding_backend": "stable-token-hash-v1",
      "embedding_dimensions": 64,
      "embedding_document_count": 15,
      "mass_rule": "blended historical topic volume with stable-token-hash embedding density; compact semantic clusters pull harder than diffuse receipt piles",
      "mass_rank": 6,
      "mass_share_of_sun": 0.13543,
      "relative_mass_to_largest_planet": 0.82114,
      "radius_scale": 0.95496
    }
  ],
  "provenance": {
    "builder": "community-solar-systems-factory",
    "source": "Community Archive raw archive + Supabase incremental dumps",
    "archive_file": "data/archive.json",
    "archive_posts": "data/archive_posts.jsonl",
    "updates_dir": "data/updates",
    "merged_posts": "data/merged_posts.jsonl",
    "trust_os_mapping": {
      "sun": "account corpus gravity center",
      "planet": "visitable topic cluster",
      "artifact": "dated quote-backed archive receipt"
    },
    "embedding_metrics": {
      "schema": "community-solar-embeddings/v1",
      "generated_at": "2026-06-29T19:28:39.684966+00:00",
      "backend": "stable-token-hash-v1",
      "dimensions": 64,
      "privacy_boundary": "derived from public Community Archive text already present in this repository; no persistent identity capture added"
    }
  }
}
